<?xml version="1.0" encoding="utf-8" ?>
<Patch>
<Operation Class="PatchOperationSequence">
		<success>Always</success>
		<operations>

			<li Class="CombatExtended.PatchOperationFindMod">
				<modName>Vanilla Weapons Expanded</modName>
			</li>
            <li Class="PatchOperationReplace">
                <xpath>Defs/ThingDef[defName="VWE_Gun_HandCannon"]/verbs/li/verbClass</xpath>
                <value><verbClass>Jams_nmags.Verb_ShootWithReliability</verbClass></value>
            </li>
            <li Class="PatchOperationAdd">
                <xpath>Defs/ThingDef[defName="VWE_Gun_HandCannon"]/comps</xpath>
                <value>
                <li Class="Jams_nmags.ReliabilityCompProps">
                    <Reliability>9990</Reliability>
                </li>
                </value>
            </li>


             <li Class="PatchOperationReplace">
                <xpath>Defs/ThingDef[defName="VWE_CombatHandgun"]/verbs/li/verbClass</xpath>
                <value><verbClass>Jams_nmags.Verb_ShootWithReliability</verbClass></value>
            </li>
            <li Class="PatchOperationAdd">
                <xpath>Defs/ThingDef[defName="VWE_CombatHandgun"]/comps</xpath>
                <value>
                <li Class="Jams_nmags.ReliabilityCompProps">
                    <Reliability>9850</Reliability>
                </li>
                </value>
            </li>




             <li Class="PatchOperationReplace">
                <xpath>Defs/ThingDef[defName="VWE_Gun_SemiAutomaticRifle"]/verbs/li/verbClass</xpath>
                <value><verbClass>Jams_nmags.Verb_ShootWithReliability</verbClass></value>
            </li>
            <li Class="PatchOperationAdd">
                <xpath>Defs/ThingDef[defName="VWE_Gun_SemiAutomaticRifle"]/comps</xpath>
                <value>
                <li Class="Jams_nmags.ReliabilityCompProps">
                    <Reliability>8550</Reliability>
                </li>
                </value>
            </li>



             <li Class="PatchOperationReplace">
                <xpath>Defs/ThingDef[defName="VWE_Gun_LeverActionRifle"]/verbs/li/verbClass</xpath>
                <value><verbClass>Jams_nmags.Verb_ShootWithReliability</verbClass></value>
            </li>
            <li Class="PatchOperationAdd">
                <xpath>Defs/ThingDef[defName="VWE_Gun_LeverActionRifle"]/comps</xpath>
                <value>
                <li Class="Jams_nmags.ReliabilityCompProps">
                    <Reliability>9550</Reliability>
                </li>
                </value>
            </li>


            <li Class="PatchOperationReplace">
                <xpath>Defs/ThingDef[defName="VWE_Gun_LightSMG"]/verbs/li/verbClass</xpath>
                <value><verbClass>Jams_nmags.Verb_ShootWithReliability</verbClass></value>
            </li>
            <li Class="PatchOperationAdd">
                <xpath>Defs/ThingDef[defName="VWE_Gun_LightSMG"]/comps</xpath>
                <value>
                <li Class="Jams_nmags.ReliabilityCompProps">
                    <Reliability>9985</Reliability>
                </li>
                </value>
            </li>


            <li Class="PatchOperationReplace">
                <xpath>Defs/ThingDef[defName="VWE_Gun_SMG"]/verbs/li/verbClass</xpath>
                <value><verbClass>Jams_nmags.Verb_ShootWithReliability</verbClass></value>
            </li>
            <li Class="PatchOperationAdd">
                <xpath>Defs/ThingDef[defName="VWE_Gun_SMG"]/comps</xpath>
                <value>
                <li Class="Jams_nmags.ReliabilityCompProps">
                    <Reliability>9885</Reliability>
                </li>
                </value>
            </li>


            <li Class="PatchOperationReplace">
                <xpath>Defs/ThingDef[defName="VWE_Gun_HMG"]/verbs/li/verbClass</xpath>
                <value><verbClass>Jams_nmags.Verb_ShootWithReliability</verbClass></value>
            </li>
            <li Class="PatchOperationAdd">
                <xpath>Defs/ThingDef[defName="VWE_Gun_HMG"]/comps</xpath>
                <value>
                <li Class="Jams_nmags.ReliabilityCompProps">
                    <Reliability>9255</Reliability>
                </li>
                </value>
            </li>



            <li Class="PatchOperationReplace">
                <xpath>Defs/ThingDef[defName="VWE_Gun_ServiceRifle"]/verbs/li/verbClass</xpath>
                <value><verbClass>Jams_nmags.Verb_ShootWithReliability</verbClass></value>
            </li>
            <li Class="PatchOperationAdd">
                <xpath>Defs/ThingDef[defName="VWE_Gun_ServiceRifle"]/comps</xpath>
                <value>
                <li Class="Jams_nmags.ReliabilityCompProps">
                    <Reliability>9985</Reliability>
                </li>
                </value>
            </li>


             <li Class="PatchOperationReplace">
                <xpath>Defs/ThingDef[defName="VWE_Gun_BattleRifle"]/verbs/li/verbClass</xpath>
                <value><verbClass>Jams_nmags.Verb_ShootWithReliability</verbClass></value>
            </li>
            <li Class="PatchOperationAdd">
                <xpath>Defs/ThingDef[defName="VWE_Gun_BattleRifle"]/comps</xpath>
                <value>
                <li Class="Jams_nmags.ReliabilityCompProps">
                    <Reliability>9950</Reliability>
                </li>
                </value>
            </li>



             <li Class="PatchOperationReplace">
                <xpath>Defs/ThingDef[defName="VWE_Gun_Carbine"]/verbs/li/verbClass</xpath>
                <value><verbClass>Jams_nmags.Verb_ShootWithReliability</verbClass></value>
            </li>
            <li Class="PatchOperationAdd">
                <xpath>Defs/ThingDef[defName="VWE_Gun_Carbine"]/comps</xpath>
                <value>
                <li Class="Jams_nmags.ReliabilityCompProps">
                    <Reliability>9790</Reliability>
                </li>
                </value>
            </li>



             <li Class="PatchOperationReplace">
                <xpath>Defs/ThingDef[defName="VWE_Gun_MarksmanRifle"]/verbs/li/verbClass</xpath>
                <value><verbClass>Jams_nmags.Verb_ShootWithReliability</verbClass></value>
            </li>
            <li Class="PatchOperationAdd">
                <xpath>Defs/ThingDef[defName="VWE_Gun_MarksmanRifle"]/comps</xpath>
                <value>
                <li Class="Jams_nmags.ReliabilityCompProps">
                    <Reliability>8890</Reliability>
                </li>
                </value>
            </li>


            
             <li Class="PatchOperationReplace">
                <xpath>Defs/ThingDef[defName="VWE_Gun_AntiMaterialRifle"]/verbs/li/verbClass</xpath>
                <value><verbClass>Jams_nmags.Verb_ShootWithReliability</verbClass></value>
            </li>
            <li Class="PatchOperationAdd">
                <xpath>Defs/ThingDef[defName="VWE_Gun_AntiMaterialRifle"]/comps</xpath>
                <value>
                <li Class="Jams_nmags.ReliabilityCompProps">
                    <Reliability>9990</Reliability>
                </li>
                </value>
            </li>



            
            
        </operations>
</Operation>
</Patch>